{
  "project": "China trip",
  "range": {
    "start": "2026-04-13",
    "end": "2026-05-14"
  },
  "attendees": [
    {
      "name": "Brian",
      "age": 43
    },
    {
      "name": "Val",
      "age": 41
    },
    {
      "name": "Harrison",
      "age": 10
    }
  ],
  "tickets": {
    "outbound": [
      {
        "flight": "UA565",
        "from": "Toronto (YYZ)",
        "to": "San Francisco (SFO)",
        "depart": "2026-04-13 07:00 EST",
        "arrive": "2026-04-13 09:39 PST"
      },
      {
        "flight": "UA869",
        "from": "San Francisco (SFO)",
        "to": "Hong Kong (HKG)",
        "depart": "2026-04-13 12:55 PST",
        "arrive": "2026-04-14 18:55 HKT"
      }
    ],
    "return": [
      {
        "flight": "UA878",
        "from": "Hong Kong (HKG)",
        "to": "San Francisco (SFO)",
        "depart": "2026-05-14 22:30 HKT",
        "arrive": "2026-05-14 20:05 PST"
      },
      {
        "flight": "UA436",
        "from": "San Francisco (SFO)",
        "to": "Toronto (YYZ)",
        "depart": "2026-05-14 23:00 PST",
        "arrive": "2026-05-15 07:00 EST"
      }
    ],
    "confirmationNumber": "NRPL6D",
    "traveler": "MILNE/BRIAN",
    "eTicketNumber": "0162341159229",
    "seats": {
      "YYZ-SFO": "30B",
      "SFO-HKG": "43B",
      "HKG-SFO": "43K",
      "SFO-YYZ": "31B"
    },
    "purchase": {
      "date": "2025-10-18",
      "method": "MasterCard ending in 3252",
      "totalPerPassengerCAD": 1041.23,
      "passengerCount": 3,
      "estimatedFamilyFlightTotalCAD": 3123.69
    }
  },
  "itinerary": [
    {
      "date": "2026-04-13",
      "weekday": "Monday",
      "city": "Hong Kong -> Huizhou",
      "stayArea": "惠东县碧桂园十里银滩三期海悦湾28号楼一单元3002",
      "attraction": {
        "name": "Hong Kong International Airport Arrival",
        "url": "https://www.hongkongairport.com/",
        "img": "https://images.unsplash.com/photo-1506970845246-18f21d533b20?auto=format&fit=crop&w=1200&q=80"
      },
      "schedule": [
        {
          "time": "07:00",
          "plan": "UA565 YYZ -> SFO departs",
          "type": "travel"
        },
        {
          "time": "12:55",
          "plan": "UA869 SFO -> HKG departs",
          "type": "travel"
        },
        {
          "time": "22:00",
          "plan": "Arrive at uncle's home, light meal, sleep",
          "type": "rest"
        }
      ],
      "estimatedCostCAD": 2520,
      "notes": "Arrival day: Uncle Tang Qi (唐淇, 13692277013) picks up family at HKG and drives directly to home in Huizhou. No subway transfer."
    },
    {
      "date": "2026-04-14",
      "weekday": "Tuesday",
      "city": "Huizhou (Huidong, Guangdong)",
      "stayArea": "碧桂园十里银滩三期海悦湾28号楼一单元3002",
      "attraction": {
        "name": "Xunliao Bay / Shili Yintan Beach",
        "url": "https://en.wikipedia.org/wiki/Huidong_County",
        "img": "https://images.unsplash.com/photo-1507525428034-b723cf961d3e?auto=format&fit=crop&w=1200&q=80"
      },
      "schedule": [
        {
          "time": "09:00",
          "plan": "Beachfront walk + light stretch (jet lag recovery)",
          "type": "activity"
        },
        {
          "time": "14:30",
          "plan": "Beach time / kids sand play / swim if weather is good",
          "type": "activity"
        },
        {
          "time": "20:30",
          "plan": "Rest / prep for next day",
          "type": "rest"
        }
      ],
      "estimatedCostCAD": 540,
      "notes": "Transfer from Hong Kong to 惠东县碧桂园十里银滩三期海悦湾28号楼一单元3002. Contact: 唐淇 13692277013. Uncle Tang Qi pickup confirmed on arrival evening from Hong Kong transit area to Huizhou home address."
    },
    {
      "date": "2026-04-15",
      "weekday": "Wednesday",
      "city": "Huizhou (Huidong, Guangdong)",
      "stayArea": "碧桂园十里银滩三期海悦湾28号楼一单元3002",
      "attraction": {
        "name": "Xunliao Bay / Shili Yintan Beach",
        "url": "https://en.wikipedia.org/wiki/Huidong_County",
        "img": "https://images.unsplash.com/photo-1507525428034-b723cf961d3e?auto=format&fit=crop&w=1200&q=80"
      },
      "schedule": [
        {
          "time": "09:00",
          "plan": "Beachfront walk + light stretch (jet lag recovery)",
          "type": "activity"
        },
        {
          "time": "14:30",
          "plan": "Beach time / kids sand play / swim if weather is good",
          "type": "activity"
        },
        {
          "time": "20:30",
          "plan": "Rest / prep for next day",
          "type": "rest"
        }
      ],
      "estimatedCostCAD": 480,
      "notes": "Second beach recovery day for jet lag reset."
    },
    {
      "date": "2026-04-16",
      "weekday": "Thursday",
      "city": "Shenzhen",
      "stayArea": "Futian District near Civic Center / Coco Park",
      "attraction": {
        "name": "Ping An Finance Center",
        "url": "https://www.pafcskymall.cn/en/",
        "img": "https://images.unsplash.com/photo-1579273166652-ee4187f3fcb5?auto=format&fit=crop&w=1200&q=80"
      },
      "schedule": [
        {
          "time": "09:00",
          "plan": "Cross-border transfer + Futian orientation walk",
          "type": "activity"
        },
        {
          "time": "14:30",
          "plan": "Ping An Finance Center observatory",
          "type": "activity"
        },
        {
          "time": "20:30",
          "plan": "Rest / prep for next day",
          "type": "rest"
        }
      ],
      "estimatedCostCAD": 680,
      "notes": "Two-night Shenzhen stop before Yunnan."
    },
    {
      "date": "2026-04-17",
      "weekday": "Friday",
      "city": "Shenzhen",
      "stayArea": "Futian District near Civic Center / Coco Park",
      "attraction": {
        "name": "Ping An Finance Center",
        "url": "https://www.pafcskymall.cn/en/",
        "img": "https://images.unsplash.com/photo-1579273166652-ee4187f3fcb5?auto=format&fit=crop&w=1200&q=80"
      },
      "schedule": [
        {
          "time": "09:00",
          "plan": "Shenzhen Bay Park seaside walk",
          "type": "activity"
        },
        {
          "time": "14:30",
          "plan": "OCT Loft art district + family café stop",
          "type": "activity"
        },
        {
          "time": "20:30",
          "plan": "Rest / prep for next day",
          "type": "rest"
        }
      ],
      "estimatedCostCAD": 520,
      "notes": ""
    },
    {
      "date": "2026-04-18",
      "weekday": "Saturday",
      "city": "Kunming",
      "stayArea": "Nanqiang Night Market area",
      "attraction": {
        "name": "Yunnan Northbound Route",
        "url": "https://en.wikipedia.org/wiki/Yunnan",
        "img": "https://images.unsplash.com/photo-1528127269322-539801943592?auto=format&fit=crop&w=1200&q=80"
      },
      "schedule": [
        {
          "time": "09:00",
          "plan": "Fly Shenzhen -> Kunming + Green Lake easy walk",
          "type": "activity"
        },
        {
          "time": "14:30",
          "plan": "Rest + local Yunnan noodles",
          "type": "activity"
        },
        {
          "time": "20:30",
          "plan": "Rest / prep for next day",
          "type": "rest"
        }
      ],
      "estimatedCostCAD": 760,
      "notes": "Flight day to Yunnan; start of 14-night Yunnan leg."
    },
    {
      "date": "2026-04-19",
      "weekday": "Sunday",
      "city": "Kunming",
      "stayArea": "Nanqiang Night Market area",
      "attraction": {
        "name": "Yunnan Northbound Route",
        "url": "https://en.wikipedia.org/wiki/Yunnan",
        "img": "https://images.unsplash.com/photo-1528127269322-539801943592?auto=format&fit=crop&w=1200&q=80"
      },
      "schedule": [
        {
          "time": "09:00",
          "plan": "Stone Forest day trip",
          "type": "activity"
        },
        {
          "time": "14:30",
          "plan": "Kunming Old Street + flower market",
          "type": "activity"
        },
        {
          "time": "20:30",
          "plan": "Rest / prep for next day",
          "type": "rest"
        }
      ],
      "estimatedCostCAD": 590,
      "notes": ""
    },
    {
      "date": "2026-04-20",
      "weekday": "Monday",
      "city": "Kunming",
      "stayArea": "Nanqiang Night Market area",
      "attraction": {
        "name": "Yunnan Northbound Route",
        "url": "https://en.wikipedia.org/wiki/Yunnan",
        "img": "https://images.unsplash.com/photo-1528127269322-539801943592?auto=format&fit=crop&w=1200&q=80"
      },
      "schedule": [
        {
          "time": "09:00",
          "plan": "Yuantong Temple + Cuihu area",
          "type": "activity"
        },
        {
          "time": "14:30",
          "plan": "Dianchi lake sunset",
          "type": "activity"
        },
        {
          "time": "20:30",
          "plan": "Rest / prep for next day",
          "type": "rest"
        }
      ],
      "estimatedCostCAD": 590,
      "notes": ""
    },
    {
      "date": "2026-04-21",
      "weekday": "Tuesday",
      "city": "Dali",
      "stayArea": "Dali Ancient Town",
      "attraction": {
        "name": "Yunnan Northbound Route",
        "url": "https://en.wikipedia.org/wiki/Yunnan",
        "img": "https://images.unsplash.com/photo-1528127269322-539801943592?auto=format&fit=crop&w=1200&q=80"
      },
      "schedule": [
        {
          "time": "09:00",
          "plan": "HSR Kunming -> Dali + old town orientation",
          "type": "activity"
        },
        {
          "time": "14:30",
          "plan": "Renmin Road cafés + music",
          "type": "activity"
        },
        {
          "time": "20:30",
          "plan": "Rest / prep for next day",
          "type": "rest"
        }
      ],
      "estimatedCostCAD": 760,
      "notes": "Move north toward Dali."
    },
    {
      "date": "2026-04-22",
      "weekday": "Wednesday",
      "city": "Dali",
      "stayArea": "Dali Ancient Town",
      "attraction": {
        "name": "Yunnan Northbound Route",
        "url": "https://en.wikipedia.org/wiki/Yunnan",
        "img": "https://images.unsplash.com/photo-1528127269322-539801943592?auto=format&fit=crop&w=1200&q=80"
      },
      "schedule": [
        {
          "time": "09:00",
          "plan": "Erhai lakeside bike/e-bike loop",
          "type": "activity"
        },
        {
          "time": "14:30",
          "plan": "Three Pagodas scenic area",
          "type": "activity"
        },
        {
          "time": "20:30",
          "plan": "Rest / prep for next day",
          "type": "rest"
        }
      ],
      "estimatedCostCAD": 590,
      "notes": ""
    },
    {
      "date": "2026-04-23",
      "weekday": "Thursday",
      "city": "Dali",
      "stayArea": "Dali Ancient Town",
      "attraction": {
        "name": "Yunnan Northbound Route",
        "url": "https://en.wikipedia.org/wiki/Yunnan",
        "img": "https://images.unsplash.com/photo-1528127269322-539801943592?auto=format&fit=crop&w=1200&q=80"
      },
      "schedule": [
        {
          "time": "09:00",
          "plan": "Xizhou village + tie-dye workshop",
          "type": "activity"
        },
        {
          "time": "14:30",
          "plan": "Cangshan cableway viewpoints",
          "type": "activity"
        },
        {
          "time": "20:30",
          "plan": "Rest / prep for next day",
          "type": "rest"
        }
      ],
      "estimatedCostCAD": 590,
      "notes": ""
    },
    {
      "date": "2026-04-24",
      "weekday": "Friday",
      "city": "Lijiang",
      "stayArea": "Lijiang Old Town",
      "attraction": {
        "name": "Yunnan Northbound Route",
        "url": "https://en.wikipedia.org/wiki/Yunnan",
        "img": "https://images.unsplash.com/photo-1528127269322-539801943592?auto=format&fit=crop&w=1200&q=80"
      },
      "schedule": [
        {
          "time": "09:00",
          "plan": "Train Dali -> Lijiang + old town canals",
          "type": "activity"
        },
        {
          "time": "14:30",
          "plan": "Black Dragon Pool sunset",
          "type": "activity"
        },
        {
          "time": "20:30",
          "plan": "Rest / prep for next day",
          "type": "rest"
        }
      ],
      "estimatedCostCAD": 760,
      "notes": "Continue north in Yunnan."
    },
    {
      "date": "2026-04-25",
      "weekday": "Saturday",
      "city": "Lijiang",
      "stayArea": "Lijiang Old Town",
      "attraction": {
        "name": "Yunnan Northbound Route",
        "url": "https://en.wikipedia.org/wiki/Yunnan",
        "img": "https://images.unsplash.com/photo-1528127269322-539801943592?auto=format&fit=crop&w=1200&q=80"
      },
      "schedule": [
        {
          "time": "09:00",
          "plan": "Shuhe Ancient Town walk",
          "type": "activity"
        },
        {
          "time": "14:30",
          "plan": "Baisha murals + Naxi culture visit",
          "type": "activity"
        },
        {
          "time": "20:30",
          "plan": "Rest / prep for next day",
          "type": "rest"
        }
      ],
      "estimatedCostCAD": 590,
      "notes": ""
    },
    {
      "date": "2026-04-26",
      "weekday": "Sunday",
      "city": "Lijiang",
      "stayArea": "Lijiang Old Town",
      "attraction": {
        "name": "Yunnan Northbound Route",
        "url": "https://en.wikipedia.org/wiki/Yunnan",
        "img": "https://images.unsplash.com/photo-1528127269322-539801943592?auto=format&fit=crop&w=1200&q=80"
      },
      "schedule": [
        {
          "time": "09:00",
          "plan": "Yulong Snow Mountain light day",
          "type": "activity"
        },
        {
          "time": "14:30",
          "plan": "Blue Moon Valley boardwalk",
          "type": "activity"
        },
        {
          "time": "20:30",
          "plan": "Rest / prep for next day",
          "type": "rest"
        }
      ],
      "estimatedCostCAD": 590,
      "notes": ""
    },
    {
      "date": "2026-04-27",
      "weekday": "Monday",
      "city": "Shangri-La",
      "stayArea": "Dukezong Ancient Town",
      "attraction": {
        "name": "Yunnan Northbound Route",
        "url": "https://en.wikipedia.org/wiki/Yunnan",
        "img": "https://images.unsplash.com/photo-1528127269322-539801943592?auto=format&fit=crop&w=1200&q=80"
      },
      "schedule": [
        {
          "time": "09:00",
          "plan": "Drive/transfer Lijiang -> Shangri-La",
          "type": "activity"
        },
        {
          "time": "14:30",
          "plan": "Dukezong old town + prayer wheel",
          "type": "activity"
        },
        {
          "time": "20:30",
          "plan": "Rest / prep for next day",
          "type": "rest"
        }
      ],
      "estimatedCostCAD": 760,
      "notes": "Northern Yunnan highland section."
    },
    {
      "date": "2026-04-28",
      "weekday": "Tuesday",
      "city": "Shangri-La",
      "stayArea": "Dukezong Ancient Town",
      "attraction": {
        "name": "Yunnan Northbound Route",
        "url": "https://en.wikipedia.org/wiki/Yunnan",
        "img": "https://images.unsplash.com/photo-1528127269322-539801943592?auto=format&fit=crop&w=1200&q=80"
      },
      "schedule": [
        {
          "time": "09:00",
          "plan": "Songzanlin Monastery",
          "type": "activity"
        },
        {
          "time": "14:30",
          "plan": "Napahai grassland viewpoints",
          "type": "activity"
        },
        {
          "time": "20:30",
          "plan": "Rest / prep for next day",
          "type": "rest"
        }
      ],
      "estimatedCostCAD": 590,
      "notes": ""
    },
    {
      "date": "2026-04-29",
      "weekday": "Wednesday",
      "city": "Shangri-La",
      "stayArea": "Dukezong Ancient Town",
      "attraction": {
        "name": "Yunnan Northbound Route",
        "url": "https://en.wikipedia.org/wiki/Yunnan",
        "img": "https://images.unsplash.com/photo-1528127269322-539801943592?auto=format&fit=crop&w=1200&q=80"
      },
      "schedule": [
        {
          "time": "09:00",
          "plan": "Pudacuo National Park easy trails",
          "type": "activity"
        },
        {
          "time": "14:30",
          "plan": "Tibetan cultural evening",
          "type": "activity"
        },
        {
          "time": "20:30",
          "plan": "Rest / prep for next day",
          "type": "rest"
        }
      ],
      "estimatedCostCAD": 590,
      "notes": ""
    },
    {
      "date": "2026-04-30",
      "weekday": "Thursday",
      "city": "Kunming",
      "stayArea": "Airport/rail convenient stay",
      "attraction": {
        "name": "Yunnan Northbound Route",
        "url": "https://en.wikipedia.org/wiki/Yunnan",
        "img": "https://images.unsplash.com/photo-1528127269322-539801943592?auto=format&fit=crop&w=1200&q=80"
      },
      "schedule": [
        {
          "time": "09:00",
          "plan": "Fly Shangri-La -> Kunming",
          "type": "activity"
        },
        {
          "time": "14:30",
          "plan": "Packing + transfer prep",
          "type": "activity"
        },
        {
          "time": "20:30",
          "plan": "Rest / prep for next day",
          "type": "rest"
        }
      ],
      "estimatedCostCAD": 760,
      "notes": "Position for flight to Chengdu."
    },
    {
      "date": "2026-05-01",
      "weekday": "Friday",
      "city": "Kunming",
      "stayArea": "Airport/rail convenient stay",
      "attraction": {
        "name": "Yunnan Northbound Route",
        "url": "https://en.wikipedia.org/wiki/Yunnan",
        "img": "https://images.unsplash.com/photo-1528127269322-539801943592?auto=format&fit=crop&w=1200&q=80"
      },
      "schedule": [
        {
          "time": "09:00",
          "plan": "Rest morning + Yunnan final meal",
          "type": "activity"
        },
        {
          "time": "14:30",
          "plan": "Fly Kunming -> Chengdu (evening)",
          "type": "activity"
        },
        {
          "time": "20:30",
          "plan": "Rest / prep for next day",
          "type": "rest"
        }
      ],
      "estimatedCostCAD": 760,
      "notes": "End of 14-night Yunnan block."
    },
    {
      "date": "2026-05-02",
      "weekday": "Saturday",
      "city": "Chengdu",
      "stayArea": "Chunxi Road / Taikoo Li area",
      "attraction": {
        "name": "Chengdu highlights",
        "url": "https://en.wikipedia.org/wiki/Chengdu",
        "img": "https://images.unsplash.com/photo-1564349683136-77e08dba1ef7?auto=format&fit=crop&w=1200&q=80"
      },
      "schedule": [
        {
          "time": "09:00",
          "plan": "Arrival + Chunxi Road easy walk",
          "type": "activity"
        },
        {
          "time": "14:30",
          "plan": "Sichuan hotpot + early night",
          "type": "activity"
        },
        {
          "time": "20:30",
          "plan": "Rest / prep for next day",
          "type": "rest"
        }
      ],
      "estimatedCostCAD": 740,
      "notes": "Flight/arrival day from Kunming."
    },
    {
      "date": "2026-05-03",
      "weekday": "Sunday",
      "city": "Chengdu",
      "stayArea": "Chunxi Road / Taikoo Li area",
      "attraction": {
        "name": "Chengdu highlights",
        "url": "https://en.wikipedia.org/wiki/Chengdu",
        "img": "https://images.unsplash.com/photo-1564349683136-77e08dba1ef7?auto=format&fit=crop&w=1200&q=80"
      },
      "schedule": [
        {
          "time": "09:00",
          "plan": "Chengdu Panda Base early visit",
          "type": "activity"
        },
        {
          "time": "14:30",
          "plan": "Kuanzhai Alley + tea house",
          "type": "activity"
        },
        {
          "time": "20:30",
          "plan": "Rest / prep for next day",
          "type": "rest"
        }
      ],
      "estimatedCostCAD": 560,
      "notes": ""
    },
    {
      "date": "2026-05-04",
      "weekday": "Monday",
      "city": "Chengdu",
      "stayArea": "Chunxi Road / Taikoo Li area",
      "attraction": {
        "name": "Chengdu highlights",
        "url": "https://en.wikipedia.org/wiki/Chengdu",
        "img": "https://images.unsplash.com/photo-1564349683136-77e08dba1ef7?auto=format&fit=crop&w=1200&q=80"
      },
      "schedule": [
        {
          "time": "09:00",
          "plan": "People's Park + Heming tea house",
          "type": "activity"
        },
        {
          "time": "14:30",
          "plan": "Wenshu Monastery streets",
          "type": "activity"
        },
        {
          "time": "20:30",
          "plan": "Rest / prep for next day",
          "type": "rest"
        }
      ],
      "estimatedCostCAD": 560,
      "notes": ""
    },
    {
      "date": "2026-05-05",
      "weekday": "Tuesday",
      "city": "Chengdu",
      "stayArea": "Chunxi Road / Taikoo Li area",
      "attraction": {
        "name": "Chengdu highlights",
        "url": "https://en.wikipedia.org/wiki/Chengdu",
        "img": "https://images.unsplash.com/photo-1564349683136-77e08dba1ef7?auto=format&fit=crop&w=1200&q=80"
      },
      "schedule": [
        {
          "time": "09:00",
          "plan": "Dujiangyan day trip",
          "type": "activity"
        },
        {
          "time": "14:30",
          "plan": "Jinjiang riverside night stroll",
          "type": "activity"
        },
        {
          "time": "20:30",
          "plan": "Rest / prep for next day",
          "type": "rest"
        }
      ],
      "estimatedCostCAD": 560,
      "notes": ""
    },
    {
      "date": "2026-05-06",
      "weekday": "Wednesday",
      "city": "Chengdu",
      "stayArea": "Chunxi Road / Taikoo Li area",
      "attraction": {
        "name": "Chengdu highlights",
        "url": "https://en.wikipedia.org/wiki/Chengdu",
        "img": "https://images.unsplash.com/photo-1564349683136-77e08dba1ef7?auto=format&fit=crop&w=1200&q=80"
      },
      "schedule": [
        {
          "time": "09:00",
          "plan": "Flexible family day / shopping / laundry",
          "type": "activity"
        },
        {
          "time": "14:30",
          "plan": "Prepare for train to Xi'an",
          "type": "activity"
        },
        {
          "time": "20:30",
          "plan": "Rest / prep for next day",
          "type": "rest"
        }
      ],
      "estimatedCostCAD": 560,
      "notes": "Move onward to Xi'an next day."
    },
    {
      "date": "2026-05-07",
      "weekday": "Thursday",
      "city": "Xi'an",
      "stayArea": "Yongning Gate / Bell Tower area",
      "attraction": {
        "name": "Xi'an highlights",
        "url": "https://en.wikipedia.org/wiki/Xi%27an",
        "img": "https://images.unsplash.com/photo-1590602847861-f357a9332bbc?auto=format&fit=crop&w=1200&q=80"
      },
      "schedule": [
        {
          "time": "09:00",
          "plan": "HSR Chengdu -> Xi'an + Bell Tower orientation",
          "type": "activity"
        },
        {
          "time": "14:30",
          "plan": "Muslim Quarter dinner",
          "type": "activity"
        },
        {
          "time": "20:30",
          "plan": "Rest / prep for next day",
          "type": "rest"
        }
      ],
      "estimatedCostCAD": 740,
      "notes": "Arrive Xi'an by high-speed rail."
    },
    {
      "date": "2026-05-08",
      "weekday": "Friday",
      "city": "Xi'an",
      "stayArea": "Yongning Gate / Bell Tower area",
      "attraction": {
        "name": "Xi'an highlights",
        "url": "https://en.wikipedia.org/wiki/Xi%27an",
        "img": "https://images.unsplash.com/photo-1590602847861-f357a9332bbc?auto=format&fit=crop&w=1200&q=80"
      },
      "schedule": [
        {
          "time": "09:00",
          "plan": "Terracotta Army museum",
          "type": "activity"
        },
        {
          "time": "14:30",
          "plan": "City wall sunset bike",
          "type": "activity"
        },
        {
          "time": "20:30",
          "plan": "Rest / prep for next day",
          "type": "rest"
        }
      ],
      "estimatedCostCAD": 560,
      "notes": ""
    },
    {
      "date": "2026-05-09",
      "weekday": "Saturday",
      "city": "Xi'an",
      "stayArea": "Yongning Gate / Bell Tower area",
      "attraction": {
        "name": "Xi'an highlights",
        "url": "https://en.wikipedia.org/wiki/Xi%27an",
        "img": "https://images.unsplash.com/photo-1590602847861-f357a9332bbc?auto=format&fit=crop&w=1200&q=80"
      },
      "schedule": [
        {
          "time": "09:00",
          "plan": "Shaanxi History Museum",
          "type": "activity"
        },
        {
          "time": "14:30",
          "plan": "Datang Everbright City",
          "type": "activity"
        },
        {
          "time": "20:30",
          "plan": "Rest / prep for next day",
          "type": "rest"
        }
      ],
      "estimatedCostCAD": 560,
      "notes": ""
    },
    {
      "date": "2026-05-10",
      "weekday": "Sunday",
      "city": "Xi'an",
      "stayArea": "Yongning Gate / Bell Tower area",
      "attraction": {
        "name": "Xi'an highlights",
        "url": "https://en.wikipedia.org/wiki/Xi%27an",
        "img": "https://images.unsplash.com/photo-1590602847861-f357a9332bbc?auto=format&fit=crop&w=1200&q=80"
      },
      "schedule": [
        {
          "time": "09:00",
          "plan": "Great Mosque + old quarter walk",
          "type": "activity"
        },
        {
          "time": "14:30",
          "plan": "South Gate night market",
          "type": "activity"
        },
        {
          "time": "20:30",
          "plan": "Rest / prep for next day",
          "type": "rest"
        }
      ],
      "estimatedCostCAD": 560,
      "notes": ""
    },
    {
      "date": "2026-05-11",
      "weekday": "Monday",
      "city": "Xi'an",
      "stayArea": "Yongning Gate / Bell Tower area",
      "attraction": {
        "name": "Xi'an highlights",
        "url": "https://en.wikipedia.org/wiki/Xi%27an",
        "img": "https://images.unsplash.com/photo-1590602847861-f357a9332bbc?auto=format&fit=crop&w=1200&q=80"
      },
      "schedule": [
        {
          "time": "09:00",
          "plan": "Buffer day + packing",
          "type": "activity"
        },
        {
          "time": "14:30",
          "plan": "Fly/rail prep to Hong Kong",
          "type": "activity"
        },
        {
          "time": "20:30",
          "plan": "Rest / prep for next day",
          "type": "rest"
        }
      ],
      "estimatedCostCAD": 560,
      "notes": "Move to Hong Kong for departure phase."
    },
    {
      "date": "2026-05-12",
      "weekday": "Tuesday",
      "city": "Hong Kong (Departure Prep)",
      "stayArea": "Tsim Sha Tsui near Airport Express",
      "attraction": {
        "name": "Avenue of Stars",
        "url": "https://www.discoverhongkong.com/eng/explore/great-outdoor/avenue-of-stars.html",
        "img": "https://images.unsplash.com/photo-1518182170546-07661fd94144?auto=format&fit=crop&w=1200&q=80"
      },
      "schedule": [
        {
          "time": "09:00",
          "plan": "Harbourfront walk + final shopping",
          "type": "activity"
        },
        {
          "time": "14:30",
          "plan": "Family flex block / souvenirs / light sightseeing",
          "type": "activity"
        },
        {
          "time": "20:30",
          "plan": "Rest / prep for next day",
          "type": "rest"
        }
      ],
      "estimatedCostCAD": 620,
      "notes": "Final buffer days before return flight."
    },
    {
      "date": "2026-05-13",
      "weekday": "Wednesday",
      "city": "Hong Kong (Departure Prep)",
      "stayArea": "Tsim Sha Tsui near Airport Express",
      "attraction": {
        "name": "Avenue of Stars",
        "url": "https://www.discoverhongkong.com/eng/explore/great-outdoor/avenue-of-stars.html",
        "img": "https://images.unsplash.com/photo-1518182170546-07661fd94144?auto=format&fit=crop&w=1200&q=80"
      },
      "schedule": [
        {
          "time": "09:00",
          "plan": "Harbourfront walk + final shopping",
          "type": "activity"
        },
        {
          "time": "14:30",
          "plan": "Family flex block / souvenirs / light sightseeing",
          "type": "activity"
        },
        {
          "time": "20:30",
          "plan": "Rest / prep for next day",
          "type": "rest"
        }
      ],
      "estimatedCostCAD": 620,
      "notes": "Final buffer days before return flight."
    },
    {
      "date": "2026-05-14",
      "weekday": "Thursday",
      "city": "Hong Kong (Departure Prep)",
      "stayArea": "Tsim Sha Tsui near Airport Express",
      "attraction": {
        "name": "Avenue of Stars",
        "url": "https://www.discoverhongkong.com/eng/explore/great-outdoor/avenue-of-stars.html",
        "img": "https://images.unsplash.com/photo-1518182170546-07661fd94144?auto=format&fit=crop&w=1200&q=80"
      },
      "schedule": [
        {
          "time": "22:30",
          "plan": "UA878 HKG -> SFO departs",
          "type": "travel"
        },
        {
          "time": "23:00",
          "plan": "UA436 SFO -> YYZ departs",
          "type": "travel"
        }
      ],
      "estimatedCostCAD": 1400,
      "notes": "Return travel day. Toronto arrival: May 15, 07:00 EST."
    }
  ],
  "routeSummary": {
    "routingLogic": "Arrival decompress on Huizhou beach, then Shenzhen, then a 14-night Yunnan northbound route before continuing to Chengdu and Xi'an, ending with Hong Kong departure buffer.",
    "minimums": {
      "huizhouNights": 2,
      "shenzhenNights": 2,
      "yunnanNights": 14,
      "chengduNights": 5,
      "xianNights": 5
    }
  }
}